Metadata-Version: 2.1
Name: problib
Version: 0.2
Summary: Gaussian and Binomial Probability Distributions
Home-page: https://github.com/lisza/problib
Author: lisza
License: MIT
Platform: UNKNOWN
